Workbook
Name Slicer_Step: #N/A
Name Slicer_Amount_Band: #N/A
Name Slicer_Type: #N/A

Sheet START HERE
A1: PAYSIM | EXCEL PIVOTTABLES PROJECT
A3: 10,000 source-level PaySim transactions · three editable native Excel PivotTables · distinct from Static/Adaptive simulation
A5: THE BUSINESS QUESTION
A6: Where is labelled fraud concentrated by transaction amount, payment type and chronological PaySim step? Native Excel PivotTables below allow filtering and rearranging reporting fields.
A9: SOURCE-SAMPLE KPIs | from the first 10,000 transaction rows
A11: Transactions | B11: =SUM('SOURCE TRANSACTIONS'!E6:E10005) -> 10000
A12: Fraud cases | B12: =SUM('SOURCE TRANSACTIONS'!G6:G10005) -> 68
A13: Fraud rate | B13: =IFERROR(B12/B11,0) -> 0.0068
A14: Amount (synthetic units) | B14: =SUM('SOURCE TRANSACTIONS'!F6:F10005) -> 1.0354669e+09
A15: Fraud amount (synthetic units) | B15: =SUM('SOURCE TRANSACTIONS'!H6:H10005) -> 36275527
A18: KEY FINDINGS | distinct from the Static vs Adaptive evaluation
A19: • 10k–100k amount band includes 42 of 68 labelled frauds (61.8%).
A21: • The 1m+ band has 8 frauds among 123 transactions (6.50%); interpret with its small denominator.
A23: • PAYMENT leads volume (5,465), but TRANSFER has 33 frauds across 921 transactions (3.58%).
A27: EXACT SCOPE & LIMITATIONS
A28: Three native Excel PivotTables share a cache of 10,000 individual transaction rows. Right-click a PivotTable to change fields; Data > Refresh All after editing the source table.
A30: Original CSV columns: Step, Type, Amount, isFraud. Additional columns: Amount Band, Transactions=1, Fraud Cases, Fraud Amount. Account IDs and balances are not embedded.
A32: No investigations, fraud predictions, Static/Adaptive decisions or cost savings are calculated here. They belong to the separate Fraud Operations Analytics dashboard / dissertation.
A34: Input is the FIRST 10,000 rows of the PaySim 50,000-row deployment sample. Currency is NOT specified by PaySim; amounts are synthetic monetary units, not real EUR losses.
A38: SOURCE & REFERENCE
A39: Source CSV | B39: https://raw.githubusercontent.com/alice-patrick/decision-centric-fraud-framework/refs/heads/main/data/deployment/paysim_deployment_sample.csv
A42: Analytics repository | B42: https://github.com/alice-patrick/fraud-decision-analytics
A46: NAVIGATION → PIVOT - AMOUNTS | PIVOT - TYPES | PIVOT - STEPS | QUALITY CHECKS | SOURCE TRANSACTIONS

Sheet PIVOT - AMOUNTS
A1: AMOUNT BAND | NATIVE EXCEL PIVOTTABLE
A3: Native PivotTable: 10,000 original transactions · grouped by Amount Band · SUM of Transactions and SUM of Fraud Cases
A4: Click the PivotTable to open PivotTable Fields. Right-click > Refresh after data changes. Fraud rate in column D is a separate formula tied to the current row layout.
B6: Values | D6: Fraud rate
A7: Row Labels | B7: Sum of Transactions | C7: Sum of Fraud Cases
A8: Under 1k | B8: 606 | C8: 2 | D8: =IF(OR(A8="",B8=""),"",IFERROR(C8/B8,0)) -> 0.00330033
A9: 1k–10k | B9: 3856 | C9: 2 | D9: =IF(OR(A9="",B9=""),"",IFERROR(C9/B9,0)) -> 0.0005186722
A10: 10k–100k | B10: 2841 | C10: 42 | D10: =IF(OR(A10="",B10=""),"",IFERROR(C10/B10,0)) -> 0.014783527
A11: 100k–1m | B11: 2574 | C11: 14 | D11: =IF(OR(A11="",B11=""),"",IFERROR(C11/B11,0)) -> 0.0054390054
A12: 1m+ | B12: 123 | C12: 8 | D12: =IF(OR(A12="",B12=""),"",IFERROR(C12/B12,0)) -> 0.06504065
A13: Grand Total | B13: 10000 | C13: 68 | D13: =IF(OR(A13="",B13=""),"",IFERROR(C13/B13,0)) -> 0.0068
A17: AMOUNT FINDING: 10k–100k contains 42 labelled fraud cases; 1m+ has the highest rate among amount bands (8/123 = 6.50%).
A24: HOW TO EDIT → Click inside A6:C... in Excel Desktop → PivotTable Analyze → Field List → move Step / Type / Amount Band / Fraud Label among Rows, Columns and Filters. The source is weighted; always use SUM of Transactions.

Sheet PIVOT - TYPES
A1: TYPE | NATIVE EXCEL PIVOTTABLE
A3: Native PivotTable: 10,000 original transactions · grouped by Type · SUM of Transactions and SUM of Fraud Cases
A4: Click the PivotTable to open PivotTable Fields. Right-click > Refresh after data changes. Fraud rate in column D is a separate formula tied to the current row layout.
B6: Values | D6: Fraud rate
A7: Row Labels | B7: Sum of Transactions | C7: Sum of Fraud Cases | D7: =IFERROR(C7/B7,0) -> 0
A8: PAYMENT | B8: 5465 | C8: 0 | D8: =IFERROR(C8/B8,0) -> 0
A9: TRANSFER | B9: 921 | C9: 33 | D9: =IFERROR(C9/B9,0) -> 0.035830619
A10: CASH_OUT | B10: 1321 | C10: 35 | D10: =IFERROR(C10/B10,0) -> 0.026495079
A11: DEBIT | B11: 344 | C11: 0 | D11: =IFERROR(C11/B11,0) -> 0
A12: CASH_IN | B12: 1949 | C12: 0 | D12: =IFERROR(C12/B12,0) -> 0
A13: Grand Total | B13: 10000 | C13: 68
A16: TYPE FINDING: PAYMENT has the most transactions but zero labelled frauds; fraud labels here are concentrated in TRANSFER and CASH_OUT.
A24: HOW TO EDIT → Click inside A6:C... in Excel Desktop → PivotTable Analyze → Field List → move Step / Type / Amount Band / Fraud Label among Rows, Columns and Filters. The source is weighted; always use SUM of Transactions.

Sheet PIVOT - STEPS
A1: STEP | NATIVE EXCEL PIVOTTABLE
A3: Native PivotTable: 10,000 original transactions · grouped by Step · SUM of Transactions and SUM of Fraud Cases
A4: Click the PivotTable to open PivotTable Fields. Right-click > Refresh after data changes. Fraud rate in column D is a separate formula tied to the current row layout.
B6: Values | D6: Fraud rate
A7: Row Labels | B7: Sum of Transactions | C7: Sum of Fraud Cases | D7: =IFERROR(C7/B7,0) -> 0
A8: 1 | B8: 2708 | C8: 16 | D8: =IFERROR(C8/B8,0) -> 0.0059084195
A9: 2 | B9: 1014 | C9: 8 | D9: =IFERROR(C9/B9,0) -> 0.0078895464
A10: 3 | B10: 552 | C10: 4 | D10: =IFERROR(C10/B10,0) -> 0.0072463768
A11: 4 | B11: 565 | C11: 10 | D11: =IFERROR(C11/B11,0) -> 0.017699115
A12: 5 | B12: 665 | C12: 6 | D12: =IFERROR(C12/B12,0) -> 0.0090225564
A13: 6 | B13: 1660 | C13: 22 | D13: =IFERROR(C13/B13,0) -> 0.013253012
A14: 7 | B14: 2836 | C14: 2 | D14: =IFERROR(C14/B14,0) -> 0.00070521862
A15: Grand Total | B15: 10000 | C15: 68
A20: STEP FINDING: Simulation steps are PaySim time periods, NOT calendar days. Higher volumes and higher fraud rates need not occur in the same step.
A24: HOW TO EDIT → Click inside A6:C... in Excel Desktop → PivotTable Analyze → Field List → move Step / Type / Amount Band / Fraud Label among Rows, Columns and Filters. The source is weighted; always use SUM of Transactions.

Sheet QUALITY CHECKS
A1: DATA QUALITY | RECONCILIATION
A3: Validation of 10,000 transaction-level PaySim records and native PivotTable totals; expected values come from the original GitHub CSV.
A5: Control | B5: Expected | C5: Calculated in Excel | D5: Outcome
A6: Transaction-level record count | B6: 10000 | C6: =SUM('SOURCE TRANSACTIONS'!E6:E10005) -> 10000 | D6: =IF(B6=C6,"PASS","CHECK") -> PASS
A7: Labelled fraud cases | B7: 68 | C7: =SUM('SOURCE TRANSACTIONS'!G6:G10005) -> 68 | D7: =IF(B7=C7,"PASS","CHECK") -> PASS
A8: Individual source records | B8: 10000 | C8: =COUNTA('SOURCE TRANSACTIONS'!A6:A10005) -> 10000 | D8: =IF(B8=C8,"PASS","CHECK") -> PASS
A9: Fraud labels reconcile | B9: 68 | C9: =SUMIF('SOURCE TRANSACTIONS'!D6:D10005,1,'SOURCE TRANSACTIONS'!E6:E10005) -> 68 | D9: =IF(B9=C9,"PASS","CHECK") -> PASS
A10: Amount Pivot transactions | B10: =C12 -> 10000 | C10: {=INDEX('PIVOT - AMOUNTS'!B:B,MATCH("Grand Total",'PIVOT - AMOUNTS'!A:A,0))} -> 10000 | D10: =IF(B10=C10,"PASS","CHECK") -> PASS
A11: Amount Pivot fraud cases | B11: =C13 -> 68 | C11: {=INDEX('PIVOT - AMOUNTS'!C:C,MATCH("Grand Total",'PIVOT - AMOUNTS'!A:A,0))} -> 68 | D11: =IF(B11=C11,"PASS","CHECK") -> PASS
A12: Type Pivot transactions | B12: =C14 -> 10000 | C12: {=INDEX('PIVOT - TYPES'!B:B,MATCH("Grand Total",'PIVOT - TYPES'!A:A,0))} -> 10000 | D12: =IF(B12=C12,"PASS","CHECK") -> PASS
A13: Type Pivot fraud cases | B13: =C15 -> 68 | C13: {=INDEX('PIVOT - TYPES'!C:C,MATCH("Grand Total",'PIVOT - TYPES'!A:A,0))} -> 68 | D13: =IF(B13=C13,"PASS","CHECK") -> PASS
A14: Step Pivot transactions | B14: =C10 -> 10000 | C14: {=INDEX('PIVOT - STEPS'!B:B,MATCH("Grand Total",'PIVOT - STEPS'!A:A,0))} -> 10000 | D14: =IF(B14=C14,"PASS","CHECK") -> PASS
A15: Step Pivot fraud cases | B15: =C11 -> 68 | C15: {=INDEX('PIVOT - STEPS'!C:C,MATCH("Grand Total",'PIVOT - STEPS'!A:A,0))} -> 68 | D15: =IF(B15=C15,"PASS","CHECK") -> PASS
A18: SOURCE-LEVEL QUALITY CHECKS | selected reporting columns
A20: Blank cells in reporting table | B20: 0 | C20: =COUNTBLANK('SOURCE TRANSACTIONS'!A6:H10005) -> 0
A21: Exact duplicates in 11-column source CSV | B21: 0 | C21: Verified on original CSV; ID columns are not in this workbook
A22: Non-positive transaction amounts | B22: 0 | C22: =COUNTIF('SOURCE TRANSACTIONS'!F6:F10005,"<=0") -> 0
A23: Account-balance checks | B23: Not measured here | C23: Not assessed: balance columns intentionally excluded
A26: Interpretation: dataset is synthetic. Fraud amount is the total amount of labelled fraud transactions, not confirmed financial loss. Excel checks cover selected fields only.

Sheet SOURCE TRANSACTIONS
A1: SOURCE TRANSACTIONS | PAYSIM 10K
A3: 10,000 individual PaySim transactions from the published deployment CSV; original Step, Type, Amount and Fraud Label retained.
A4: One row per transaction. Amount Band, Transactions=1, Fraud Cases and Fraud Amount are derived reporting columns; no account identifiers included.
A5: Step | B5: Type | C5: Amount Band | D5: Fraud Label | E5: Transactions | F5: Total Amount | G5: Fraud Cases | H5: Fraud Amount
A6: 1 | B6: PAYMENT | C6: 1k–10k | D6: 0 | E6: 1 | F6: 9839.64 | G6: 0 | H6: 0
A7: 1 | B7: PAYMENT | C7: 1k–10k | D7: 0 | E7: 1 | F7: 1864.28 | G7: 0 | H7: 0
A8: 1 | B8: TRANSFER | C8: Under 1k | D8: 1 | E8: 1 | F8: 181 | G8: 1 | H8: 181
A9: 1 | B9: CASH_OUT | C9: Under 1k | D9: 1 | E9: 1 | F9: 181 | G9: 1 | H9: 181
A10: 1 | B10: PAYMENT | C10: 10k–100k | D10: 0 | E10: 1 | F10: 11668.14 | G10: 0 | H10: 0
A11: 1 | B11: PAYMENT | C11: 1k–10k | D11: 0 | E11: 1 | F11: 7817.71 | G11: 0 | H11: 0
A12: 1 | B12: PAYMENT | C12: 1k–10k | D12: 0 | E12: 1 | F12: 7107.77 | G12: 0 | H12: 0
A13: 1 | B13: PAYMENT | C13: 1k–10k | D13: 0 | E13: 1 | F13: 7861.64 | G13: 0 | H13: 0
A14: 1 | B14: PAYMENT | C14: 1k–10k | D14: 0 | E14: 1 | F14: 4024.36 | G14: 0 | H14: 0
A15: 1 | B15: DEBIT | C15: 1k–10k | D15: 0 | E15: 1 | F15: 5337.77 | G15: 0 | H15: 0
A16: 1 | B16: DEBIT | C16: 1k–10k | D16: 0 | E16: 1 | F16: 9644.94 | G16: 0 | H16: 0
A17: 1 | B17: PAYMENT | C17: 1k–10k | D17: 0 | E17: 1 | F17: 3099.97 | G17: 0 | H17: 0
... A10005: 7 | B10005: PAYMENT | C10005: 1k–10k | D10005: 0 | E10005: 1 | F10005: 5096.16 | G10005: 0 | H10005: 0

Sheet DASHBOARD
A1: PAYSim | FRAUD ANALYTICS DASHBOARD
A3: PORTFOLIO PROJECT • 10,000 SYNTHETIC TRANSACTIONS • FIRST 7 PAYSIM STEPS
A5: TRANSACTIONS | D5: FRAUD CASES | G5: FRAUD RATE | J5: TOTAL AMOUNT — FULL SAMPLE (SYNTHETIC)
A6: ='QUALITY CHECKS'!C10 -> 10000 | D6: ='QUALITY CHECKS'!C11 -> 68 | G6: =IFERROR(D6/A6,0) -> 0.0068 | J6: =SUM('SOURCE TRANSACTIONS'!F6:F10005) -> 1.0354669e+09
A8: FRAUD BY AMOUNT BAND | I8: FRAUD BY PAYMENT TYPE
A24: FRAUD RATE ACROSS PAYSIM STEPS
A42: DATA TABLE: AMOUNT BANDS | F42: DATA TABLE: TRANSACTION TYPES | K42: DATA TABLE: STEPS
A43: Amount Band | B43: Transactions | C43: Fraud Cases | D43: Fraud Rate | F43: Type | G43: Transactions | H43: Fraud Cases | I43: Fraud Rate | K43: Step | L43: Transactions | M43: Fraud Cases | N43: Fraud Rate
A44: Under 1k | B44: =SUMIF('PIVOT - AMOUNTS'!$A$8:$A$13,A44,'PIVOT - AMOUNTS'!$B$8:$B$13) -> 606 | C44: =SUMIF('PIVOT - AMOUNTS'!$A$8:$A$13,A44,'PIVOT - AMOUNTS'!$C$8:$C$13) -> 2 | D44: =IFERROR(C44/B44,0) -> 0.00330033 | F44: PAYMENT | G44: =SUMIF('PIVOT - TYPES'!$A$8:$A$13,F44,'PIVOT - TYPES'!$B$8:$B$13) -> 5465 | H44: =SUMIF('PIVOT - TYPES'!$A$8:$A$13,F44,'PIVOT - TYPES'!$C$8:$C$13) -> 0 | I44: =IFERROR(H44/G44,0) -> 0 | K44: 1 | L44: {=SUMPRODUCT(--('PIVOT - STEPS'!$A$8:$A$14=K44),'PIVOT - STEPS'!$B$8:$B$14)} -> 2708 | M44: {=SUMPRODUCT(--('PIVOT - STEPS'!$A$8:$A$14=K44),'PIVOT - STEPS'!$C$8:$C$14)} -> 16 | N44: =IFERROR(M44/L44,0) -> 0.0059084195
A45: 1k–10k | B45: =SUMIF('PIVOT - AMOUNTS'!$A$8:$A$13,A45,'PIVOT - AMOUNTS'!$B$8:$B$13) -> 3856 | C45: =SUMIF('PIVOT - AMOUNTS'!$A$8:$A$13,A45,'PIVOT - AMOUNTS'!$C$8:$C$13) -> 2 | D45: =IFERROR(C45/B45,0) -> 0.0005186722 | F45: TRANSFER | G45: ='PIVOT - TYPES'!B9 -> 921 | H45: ='PIVOT - TYPES'!C9 -> 33 | I45: =IFERROR(H45/G45,0) -> 0.035830619 | K45: 2 | L45: {=SUMPRODUCT(--('PIVOT - STEPS'!$A$8:$A$14=K45),'PIVOT - STEPS'!$B$8:$B$14)} -> 1014 | M45: {=SUMPRODUCT(--('PIVOT - STEPS'!$A$8:$A$14=K45),'PIVOT - STEPS'!$C$8:$C$14)} -> 8 | N45: =IFERROR(M45/L45,0) -> 0.0078895464
A46: 10k–100k | B46: =SUMIF('PIVOT - AMOUNTS'!$A$8:$A$13,A46,'PIVOT - AMOUNTS'!$B$8:$B$13) -> 2841 | C46: =SUMIF('PIVOT - AMOUNTS'!$A$8:$A$13,A46,'PIVOT - AMOUNTS'!$C$8:$C$13) -> 42 | D46: =IFERROR(C46/B46,0) -> 0.014783527 | F46: CASH_OUT | G46: ='PIVOT - TYPES'!B10 -> 1321 | H46: ='PIVOT - TYPES'!C10 -> 35 | I46: =IFERROR(H46/G46,0) -> 0.026495079 | K46: 3 | L46: {=SUMPRODUCT(--('PIVOT - STEPS'!$A$8:$A$14=K46),'PIVOT - STEPS'!$B$8:$B$14)} -> 552 | M46: {=SUMPRODUCT(--('PIVOT - STEPS'!$A$8:$A$14=K46),'PIVOT - STEPS'!$C$8:$C$14)} -> 4 | N46: =IFERROR(M46/L46,0) -> 0.0072463768
A47: 100k–1m | B47: =SUMIF('PIVOT - AMOUNTS'!$A$8:$A$13,A47,'PIVOT - AMOUNTS'!$B$8:$B$13) -> 2574 | C47: =SUMIF('PIVOT - AMOUNTS'!$A$8:$A$13,A47,'PIVOT - AMOUNTS'!$C$8:$C$13) -> 14 | D47: =IFERROR(C47/B47,0) -> 0.0054390054 | F47: DEBIT | G47: ='PIVOT - TYPES'!B11 -> 344 | H47: ='PIVOT - TYPES'!C11 -> 0 | I47: =IFERROR(H47/G47,0) -> 0 | K47: 4 | L47: {=SUMPRODUCT(--('PIVOT - STEPS'!$A$8:$A$14=K47),'PIVOT - STEPS'!$B$8:$B$14)} -> 565 | M47: {=SUMPRODUCT(--('PIVOT - STEPS'!$A$8:$A$14=K47),'PIVOT - STEPS'!$C$8:$C$14)} -> 10 | N47: =IFERROR(M47/L47,0) -> 0.017699115
A48: 1m+ | B48: =SUMIF('PIVOT - AMOUNTS'!$A$8:$A$13,A48,'PIVOT - AMOUNTS'!$B$8:$B$13) -> 123 | C48: =SUMIF('PIVOT - AMOUNTS'!$A$8:$A$13,A48,'PIVOT - AMOUNTS'!$C$8:$C$13) -> 8 | D48: =IFERROR(C48/B48,0) -> 0.06504065 | F48: CASH_IN | G48: ='PIVOT - TYPES'!B12 -> 1949 | H48: ='PIVOT - TYPES'!C12 -> 0 | I48: =IFERROR(H48/G48,0) -> 0 | K48: 5 | L48: ='PIVOT - STEPS'!B12 -> 665 | M48: {=SUMPRODUCT(--('PIVOT - STEPS'!$A$8:$A$14=K48),'PIVOT - STEPS'!$C$8:$C$14)} -> 6 | N48: =IFERROR(M48/L48,0) -> 0.0090225564
K49: 6 | L49: ='PIVOT - STEPS'!B13 -> 1660 | M49: {=SUMPRODUCT(--('PIVOT - STEPS'!$A$8:$A$14=K49),'PIVOT - STEPS'!$C$8:$C$14)} -> 22 | N49: =IFERROR(M49/L49,0) -> 0.013253012
K50: 7 | L50: ='PIVOT - STEPS'!B14 -> 2836 | M50: {=SUMPRODUCT(--('PIVOT - STEPS'!$A$8:$A$14=K50),'PIVOT - STEPS'!$C$8:$C$14)} -> 2 | N50: =IFERROR(M50/L50,0) -> 0.00070521862
A54: BUSINESS TAKEAWAYS | FULL 10,000-TRANSACTION SAMPLE
A55: 10k–100k contains 42/68 fraud labels (61.8%) despite lower rate than the 1m+ band.
A56: TRANSFER and CASH_OUT contain all 68 observed fraud labels in this synthetic sample.
A57: Rates for small groups must be interpreted cautiously; this is descriptive, not predictive analysis.
A59: SCOPE: 10,000 first PaySim rows only. Fraud Amount is not confirmed financial loss.
A60: METHOD: Values linked to original native Excel PivotTables; charts recalculate on Excel refresh.
